traffic_light.v
module traffic_light(
    input clk,
    input rst,
    output reg [2:0] light
);

parameter RED    = 3'b100;
parameter YELLOW = 3'b010;
parameter GREEN  = 3'b001;

reg [1:0] state;

always @(posedge clk or posedge rst)
begin
    if(rst)
    begin
        state <= 0;
        light <= RED;
    end
    else
    begin
        case(state)
            0: begin
                light <= RED;
                state <= 1;
            end

            1: begin
                light <= GREEN;
                state <= 2;
            end

            2: begin
                light <= YELLOW;
                state <= 0;
            end
        endcase
    end
end

endmodule

traffic_light_tb.v
`timescale 1ns/1ps

module traffic_light_tb;

reg clk;
reg rst;
wire [2:0] light;

traffic_light uut(
    .clk(clk),
    .rst(rst),
    .light(light)
);

always #5 clk = ~clk;

initial
begin
    clk = 0;
    rst = 1;

    #10 rst = 0;

    #100 $finish;
end
initial begin
    $dumpfile("traffic.vcd");
    $dumpvars(0, traffic_light_tb);
end

initial
begin
    $monitor("Time=%0t Light=%b", $time, light);
end

endmodule

traffic.vcd
$date
	Mon Jun 01 12:49:49 2026
$end
$version
	Icarus Verilog
$end
$timescale
	1ps
$end
$scope module traffic_light_tb $end
$var wire 3 ! light [2:0] $end
$var reg 1 " clk $end
$var reg 1 # rst $end
$scope module uut $end
$var wire 1 " clk $end
$var wire 1 # rst $end
$var parameter 3 $ GREEN $end
$var parameter 3 % RED $end
$var parameter 3 & YELLOW $end
$var reg 3 ' light [2:0] $end
$var reg 2 ( state [1:0] $end
$upscope $end
$upscope $end
$enddefinitions $end
$comment Show the parameter values. $end
$dumpall
b10 &
b100 %
b1 $
$end
#0
$dumpvars
b0 (
b100 '
1#
0"
b100 !
$end
#5000
1"
#10000
0"
0#
#15000
b1 (
1"
#20000
0"
#25000
b10 (
b1 !
b1 '
1"
#30000
0"
#35000
b0 (
b10 !
b10 '
1"
#40000
0"
#45000
b1 (
b100 !
b100 '
1"
#50000
0"
#55000
b10 (
b1 !
b1 '
1"
#60000
0"
#65000
b0 (
b10 !
b10 '
1"
#70000
0"
#75000
b1 (
b100 !
b100 '
1"
#80000
0"
#85000
b10 (
b1 !
b1 '
1"
#90000
0"
#95000
b0 (
b10 !
b10 '
1"
#100000
0"
#105000
b1 (
b100 !
b100 '
1"
